README.md
license.txt
setup.cfg
setup.py
.github/workflows/ci.yaml
strippng/__init__.py
strippng/__main__.py
strippng/py.typed
strippng/strippng.py
strippng/version.py
strippng.egg-info/PKG-INFO
strippng.egg-info/SOURCES.txt
strippng.egg-info/dependency_links.txt
strippng.egg-info/top_level.txt
test/.gitattributes
test/5c-marketing-analysis.png
test/test_strippng.py